[
  {
    "id": 1,
    "name": "cleaningServices",
    "services": [
      { "id": 101, "name": "apartmentCleaning" },
      { "id": 102, "name": "computerCleaning" },
      { "id": 103, "name": "insectSpraying" },
      { "id": 104, "name": "emptyHouseCleaning" },
      { "id": 105, "name": "glassCleaning" },
      { "id": 106, "name": "windowCleaning" },
      { "id": 107, "name": "exteriorGlassWiping" },
      { "id": 108, "name": "shopCleaning" },
      { "id": 109, "name": "houseSpraying" },
      { "id": 110, "name": "houseCleaning" },
      { "id": 111, "name": "carpetCleaningAtHome" },
      { "id": 112, "name": "homeSofaWashing" },
      { "id": 113, "name": "homeIroningService" },
      { "id": 114, "name": "homeCooking" },
      { "id": 115, "name": "mouseExtermination" },
      { "id": 116, "name": "silverBeetleSpraying" },
      { "id": 117, "name": "carpetWashing" },
      { "id": 118, "name": "haliFlexWashing" },
      { "id": 119, "name": "cockroachSpraying" },
      { "id": 120, "name": "pestControl" },
      { "id": 121, "name": "postConstructionCleaning" },
      { "id": 122, "name": "heatingBeetleControl" },
      { "id": 123, "name": "antControl" },
      { "id": 124, "name": "airConditioningCleaning" },
      { "id": 125, "name": "sofaWashing" },
      { "id": 126, "name": "combiRadiatorCleaning" },
      { "id": 127, "name": "dryCleaning" },
      { "id": 128, "name": "storeWindowCleaning" },
      { "id": 129, "name": "stairCleaning" },
      { "id": 130, "name": "marblePolishing" },
      { "id": 131, "name": "marbleCleaning" },
      { "id": 132, "name": "officeCarpetCleaning" },
      { "id": 133, "name": "officeCleaning" },
      { "id": 134, "name": "radiatorCleaning" },
      { "id": 135, "name": "radiatorClean" },
      { "id": 136, "name": "fleaSpraying" },
      { "id": 137, "name": "rollerBlindWashing" },
      { "id": 138, "name": "waterTankCleaning" },
      { "id": 139, "name": "bedBugSpraying" },
      { "id": 140, "name": "makingStuffedGrapeLeaves" },
      { "id": 141, "name": "bedWashing" },
      { "id": 142, "name": "on-SiteCarSeatWashing" }
    ]

  },
  {
    "id": 2,
    "name": "renovationDecorationAndConstructionServices",
    "services": [
      { "id": 201, "name": "woodenDoor" },
      { "id": 202, "name": "plasterMaster" },
      { "id": 203, "name": "drywallCeiling" },
      { "id": 204, "name": "drywallPartitionWall" },
      { "id": 205, "name": "americanPanelDoor" },
      { "id": 206, "name": "turnkeyConstruction" },
      { "id": 207, "name": "suspendedCeiling" },
      { "id": 208, "name": "gardenMaintenance" },
      { "id": 209, "name": "gardenFenceWire" },
      { "id": 210, "name": "gardenFence" },
      { "id": 211, "name": "gardenWallConstruction" },
      { "id": 212, "name": "gardenDesign" },
      { "id": 213, "name": "gardenWire" },
      { "id": 214, "name": "gardener" },
      { "id": 215, "name": "balconyNet" },
      { "id": 216, "name": "balconyCatNet" },
      { "id": 217, "name": "bathroomCabinetConstruction" },
      { "id": 218, "name": "bathroomTileInstallation" },
      { "id": 219, "name": "bathroomRenovation" },
      { "id": 220, "name": "painting" },
      { "id": 221, "name": "glassBalcony" },
      { "id": 222, "name": "roofInsulation" },
      { "id": 223, "name": "roofRenovation" },
      { "id": 224, "name": "roofRepair" },
      { "id": 225, "name": "steelDoor" },
      { "id": 226, "name": "ironWelding" },
      { "id": 227, "name": "exteriorCladding" },
      { "id": 228, "name": "naturalGasInstallation" },
      { "id": 229, "name": "cabinetPainting" },
      { "id": 230, "name": "showerCabin" },
      { "id": 231, "name": "wallDecoration" },
      { "id": 232, "name": "wallpaperInstallation" },
      { "id": 233, "name": "wallCladding" },
      { "id": 234, "name": "housePainting" },
      { "id": 235, "name": "homeDecoration" },
      { "id": 236, "name": "homeRenovation" },
      { "id": 237, "name": "tileInstallation" },
      { "id": 238, "name": "foilCladding" },
      { "id": 239, "name": "wardrobeConstruction" },
      { "id": 240, "name": "granite" },
      { "id": 241, "name": "solarEnergy" },
      { "id": 242, "name": "poolConstruction" },
      { "id": 243, "name": "readyRollGrass" },
      { "id": 244, "name": "scrapDealer" },
      { "id": 245, "name": "interiorDoor" },
      { "id": 246, "name": "interiorDesigner" },
      { "id": 247, "name": "roughConstruction" },
      { "id": 248, "name": "paperScrapDealer" },
      { "id": 249, "name": "sofaUpholstery" },
      { "id": 250, "name": "doorScreen" },
      { "id": 251, "name": "foldingGlassBalcony" },
      { "id": 252, "name": "welding" },
      { "id": 253, "name": "catNet" },
      { "id": 254, "name": "catWindowScreen" },
      { "id": 255, "name": "catScreen" },
      { "id": 256, "name": "shutter" },
      { "id": 257, "name": "chairUpholsteryy" },
      { "id": 258, "name": "sofaCovering" },
      { "id": 259, "name": "lSofaCovering" },
      { "id": 260, "name": "laminateFlooring" },
      { "id": 261, "name": "thermalInsulation" },
      { "id": 262, "name": "carpenter" },
      { "id": 263, "name": "hingedWindowScreen" },
      { "id": 264, "name": "marble" },
      { "id": 265, "name": "marbleKitchenCounter" },
      { "id": 266, "name": "marbleCounter" },
      { "id": 267, "name": "tombConstruction" },
      { "id": 268, "name": "furniturePainting" },
      { "id": 269, "name": "kitchenDecoration" },
      { "id": 270, "name": "kitchenCabinetPainting" },
      { "id": 271, "name": "kitchenCabinetConstruction" },
      { "id": 272, "name": "kitchenRenovation" },
      { "id": 273, "name": "kitchenCounter" },
      { "id": 274, "name": "automaticDoor" },
      { "id": 275, "name": "automaticShutter" },
      { "id": 276, "name": "automaticBlind" },
      { "id": 277, "name": "panelFence" },
      { "id": 278, "name": "blind" },
      { "id": 279, "name": "parquetFlooring" },
      { "id": 280, "name": "parquetPolishing" },
      { "id": 281, "name": "cobblestonePaving" },
      { "id": 282, "name": "windowScreen" },
      { "id": 283, "name": "pvcDoor" },
      { "id": 284, "name": "pvcWindow" },
      { "id": 285, "name": "prefabricatedHouse" },
      { "id": 286, "name": "pvcWindowFrame" },
      { "id": 287, "name": "chairCovering" },
      { "id": 288, "name": "flyScreen" },
      { "id": 289, "name": "plasteringMaster" },
      { "id": 290, "name": "rollerBlind" },
      { "id": 291, "name": "waterInsulation" },
      { "id": 292, "name": "waterproofing" },
      { "id": 293, "name": "baseboardInstallation" },
      { "id": 294, "name": "slidingDoor" },
      { "id": 295, "name": "slidingWindowScreen" },
      { "id": 296, "name": "slidingScreen" },
      { "id": 297, "name": "repairRenovation" },
      { "id": 298, "name": "singleSeatCovering" },
      { "id": 299, "name": "wireMeshFence" },
      { "id": 300, "name": "awningCanvas" }
    ]

  },
  {
    "id": 3,
    "name": "transportationAndStorageServices",
    "services": [
      { "id": 301, "name": "germanyHouseMoving" },
      { "id": 302, "name": "cargoWarehouse" },
      { "id": 303, "name": "vehicleTransport" },
      { "id": 304, "name": "elevatorRental" },
      { "id": 305, "name": "elevatorTransport" },
      { "id": 306, "name": "dishwasherMoving" },
      { "id": 307, "name": "fridgeMoving" },
      { "id": 308, "name": "washingMachineMoving" },
      { "id": 309, "name": "dowryTransport" },
      { "id": 310, "name": "storageRental" },
      { "id": 311, "name": "dobloTransport" },
      { "id": 312, "name": "weddingServiceRental" },
      { "id": 313, "name": "weddingService" },
      { "id": 314, "name": "pharmacyCourier" },
      { "id": 315, "name": "itemStorage" },
      { "id": 316, "name": "itemTransport" },
      { "id": 317, "name": "indoorItemTransport" },
      { "id": 318, "name": "houseMoving" },
      { "id": 319, "name": "houseToHouseTransport" },
      { "id": 320, "name": "dailyDriver" },
      { "id": 321, "name": "porterService" },
      { "id": 322, "name": "airportTransfer" },
      { "id": 323, "name": "vanRental" },
      { "id": 324, "name": "vanTransport" },
      { "id": 325, "name": "catTransport" },
      { "id": 326, "name": "shortDistanceTransport" },
      { "id": 327, "name": "boxTransport" },
      { "id": 328, "name": "sofaTransport" },
      { "id": 329, "name": "dogTransport" },
      { "id": 330, "name": "minibusRental" },
      { "id": 331, "name": "minivanTransport" },
      { "id": 332, "name": "motorCourier" },
      { "id": 333, "name": "motorbikeTow" },
      { "id": 334, "name": "motorbikeTransport" },
      { "id": 335, "name": "officeMoving" },
      { "id": 336, "name": "carTow" },
      { "id": 337, "name": "carRecovery" },
      { "id": 338, "name": "busRental" },
      { "id": 339, "name": "privateAmbulance" },
      { "id": 340, "name": "privateDriver" },
      { "id": 341, "name": "palletLoadTransport" },
      { "id": 342, "name": "panelvanTransport" },
      { "id": 343, "name": "staffService" },
      { "id": 344, "name": "pickupTransport" },
      { "id": 345, "name": "urbanTransport" },
      { "id": 346, "name": "intercityAmbulance" },
      { "id": 347, "name": "intercityVehicleTransport" },
      { "id": 348, "name": "intercityItemTransport" },
      { "id": 349, "name": "intercityMotorbikeTransport" },
      { "id": 350, "name": "intercityTransport" },
      { "id": 351, "name": "intercityTaxi" },
      { "id": 352, "name": "intercityLoadTransport" },
      { "id": 353, "name": "chauffeuredVehicleRental" },
      { "id": 354, "name": "nonChauffeuredVanRental" },
      { "id": 355, "name": "taxiService" },
      { "id": 356, "name": "boatTransport" },
      { "id": 357, "name": "transferService" },
      { "id": 358, "name": "internationalHouseMoving" },
      { "id": 359, "name": "internationalHouseToHouse" },
      { "id": 360, "name": "internationalTransport" },
      { "id": 361, "name": "vipTransfer" },
      { "id": 362, "name": "vitoRental" },
      { "id": 363, "name": "loadTransport" },
      { "id": 364, "name": "internationalCargo" },
      { "id": 365, "name": "internationalHouseExport" }
    ]

  },
  {
    "id": 4,
    "name": "allAssemblyAndRepairServices",
    "services": [
      { "id": 401, "name": "woodenDoorRepair" },
      { "id": 402, "name": "airfelBoilerService" },
      { "id": 403, "name": "aluminumJoinery" },
      { "id": 404, "name": "americanPanelDoorInstallation" },
      { "id": 405, "name": "americanPanelDoorRepair" },
      { "id": 406, "name": "arcelikRefrigeratorService" },
      { "id": 407, "name": "arcelikAirConditionerService" },
      { "id": 408, "name": "arcelikService" },
      { "id": 409, "name": "elevatorMaintenance" },
      { "id": 410, "name": "chandelierInstallation" },
      { "id": 411, "name": "shoeRepair" },
      { "id": 412, "name": "baymakBoilerService" },
      { "id": 413, "name": "homeApplianceService" },
      { "id": 414, "name": "homeApplianceRepair" },
      { "id": 415, "name": "computerRepair" },
      { "id": 416, "name": "computerTechnician" },
      { "id": 417, "name": "boschBoilerService" },
      { "id": 418, "name": "buderusBoilerService" },
      { "id": 419, "name": "dishwasherRepair" },
      { "id": 420, "name": "refrigeratorService" },
      { "id": 421, "name": "refrigeratorRepair" },
      { "id": 422, "name": "washingMachineRepair" },
      { "id": 423, "name": "glassTechnician" },
      { "id": 424, "name": "satelliteDishAdjustment" },
      { "id": 425, "name": "satelliteDishInstallation" },
      { "id": 426, "name": "steelDoorRepair" },
      { "id": 427, "name": "locksmith" },
      { "id": 428, "name": "locksmithDoorOpening" },
      { "id": 429, "name": "demirdokumBoilerService" },
      { "id": 430, "name": "wardrobeAssembly" },
      { "id": 431, "name": "showerCabinGlassReplacement" },
      { "id": 432, "name": "showerCabinInstallation" },
      { "id": 433, "name": "showerCabinRepair" },
      { "id": 434, "name": "ecaBoilerService" },
      { "id": 435, "name": "electroluxService" },
      { "id": 436, "name": "electricity" },
      { "id": 437, "name": "electricalLineInstallation" },
      { "id": 438, "name": "electricalInstallation" },
      { "id": 439, "name": "electricalRepair" },
      { "id": 440, "name": "electrician" },
      { "id": 441, "name": "frankeService" },
      { "id": 442, "name": "wardrobeInstallation" },
      { "id": 443, "name": "videoIntercom" },
      { "id": 444, "name": "internetCableInstallation" },
      { "id": 445, "name": "iphoneRepair" },
      { "id": 446, "name": "iptvInstallation" },
      { "id": 447, "name": "cableAndLineInstallation" },
      { "id": 448, "name": "securityCameraSystems" },
      { "id": 449, "name": "cameraSystems" },
      { "id": 450, "name": "airConditionerMaintenance" },
      { "id": 451, "name": "airConditionerElectricalConnection" },
      { "id": 452, "name": "airConditionerGasFilling" },
      { "id": 453, "name": "airConditionerInstallation" },
      { "id": 454, "name": "airConditionerService" },
      { "id": 455, "name": "airConditionerNotCooling" },
      { "id": 456, "name": "airConditionerRemoval" },
      { "id": 457, "name": "airConditionerRepair" },
      { "id": 458, "name": "toiletInstallation" },
      { "id": 459, "name": "toiletLeaking" },
      { "id": 460, "name": "boilerMaintenance" },
      { "id": 461, "name": "boilerInstallation" },
      { "id": 462, "name": "boilerService" },
      { "id": 463, "name": "boilerRepair" },
      { "id": 464, "name": "curtainRodInstallation" },
      { "id": 465, "name": "lgTvService" },
      { "id": 466, "name": "mitsubishiAirConditionerService" },
      { "id": 467, "name": "furnitureAssembly" },
      { "id": 468, "name": "furnitureDismantlingTransportAndAssembly" },
      { "id": 469, "name": "faucetReplacement" },
      { "id": 470, "name": "faucetRepair" },
      { "id": 471, "name": "kitchenCabinetDoorReplacement" },
      { "id": 472, "name": "roomDoor" },
      { "id": 473, "name": "shutterRepair" },
      { "id": 474, "name": "windowGlassReplacement" },
      { "id": 475, "name": "curtainRodHanging" },
      { "id": 476, "name": "pvcDoorRepair" },
      { "id": 477, "name": "pvcWindowRepair" },
      { "id": 478, "name": "robotVacuumRepair" },
      { "id": 479, "name": "watchRepair" },
      { "id": 480, "name": "samsungTvService" },
      { "id": 481, "name": "flushRepair" },
      { "id": 482, "name": "plumbing" },
      { "id": 483, "name": "waterFilterReplacement" },
      { "id": 484, "name": "waterLeakRepair" },
      { "id": 485, "name": "waterLeakDetection" },
      { "id": 486, "name": "plumber" },
      { "id": 487, "name": "waterPiping" },
      { "id": 488, "name": "plumbingInstallation" },
      { "id": 489, "name": "slidingWardrobeRepair" },
      { "id": 490, "name": "phoneRepair" },
      { "id": 491, "name": "clogClearing" },
      { "id": 492, "name": "tvScreenRepair" },
      { "id": 493, "name": "tvLedReplacement" },
      { "id": 494, "name": "tvInstallation" },
      { "id": 495, "name": "tvPanelRepair" },
      { "id": 496, "name": "tvRepair" },
      { "id": 497, "name": "satelliteAdjustment" },
      { "id": 498, "name": "satelliteTechnician" },
      { "id": 499, "name": "vaillantBoilerService" },
      { "id": 500, "name": "dataRecovery" }
    ]

  }  ,
  {
    "id": 5,
    "name": "tutoringServices",
    "services": [
      { "id": 501, "name": "germanPrivateLesson" },
      { "id": 502, "name": "arabicPrivateLesson" },
      { "id": 503, "name": "aytMathematicsPrivateLesson" },
      { "id": 504, "name": "baglamaLesson" },
      { "id": 505, "name": "baristaTraining" },
      { "id": 506, "name": "basketballPrivateLesson" },
      { "id": 507, "name": "drumLesson" },
      { "id": 508, "name": "boxingLesson" },
      { "id": 509, "name": "childPianoLesson" },
      { "id": 510, "name": "dgsMathematicsPrivateLesson" },
      { "id": 511, "name": "dictionLesson" },
      { "id": 512, "name": "drivingLesson" },
      { "id": 513, "name": "weddingDanceLesson" },
      { "id": 514, "name": "educationCoach" },
      { "id": 515, "name": "drivingLicenseCourse" },
      { "id": 516, "name": "sciencePrivateLesson" },
      { "id": 517, "name": "fitnessPrivateLesson" },
      { "id": 518, "name": "physicsPrivateLesson" },
      { "id": 519, "name": "frenchPrivateLesson" },
      { "id": 520, "name": "footballPrivateLesson" },
      { "id": 521, "name": "guitarLesson" },
      { "id": 522, "name": "groupPilatesLesson" },
      { "id": 523, "name": "speedReadingLesson" },
      { "id": 524, "name": "elementarySchoolMathematicsPrivateLesson" },
      { "id": 525, "name": "elementarySchoolPrivateLesson" },
      { "id": 526, "name": "englishPrivateLesson" },
      { "id": 527, "name": "spanishPrivateLesson" },
      { "id": 528, "name": "violinLesson" },
      { "id": 529, "name": "kickBoxingLesson" },
      { "id": 530, "name": "chemistryPrivateLesson" },
      { "id": 531, "name": "kpssCoach" },
      { "id": 532, "name": "kpssMathematicsPrivateLesson" },
      { "id": 533, "name": "quranPrivateLesson" },
      { "id": 534, "name": "lgsMathematicsPrivateLesson" },
      { "id": 535, "name": "highSchoolMathematicsPrivateLesson" },
      { "id": 536, "name": "mathematicsPrivateLesson" },
      { "id": 537, "name": "motorDrivingLicenseCourse" },
      { "id": 538, "name": "motorcycleTraining" },
      { "id": 539, "name": "homeworkSister" },
      { "id": 540, "name": "studentCoach" },
      { "id": 541, "name": "literacyPrivateLesson" },
      { "id": 542, "name": "onlineGermanPrivateLesson" },
      { "id": 543, "name": "onlineArabicPrivateLesson" },
      { "id": 544, "name": "onlineDictionLesson" },
      { "id": 545, "name": "onlineEducationCoach" },
      { "id": 546, "name": "onlinePhysicsPrivateLesson" },
      { "id": 547, "name": "onlineFrenchPrivateLesson" },
      { "id": 548, "name": "onlineGuitarLesson" },
      { "id": 549, "name": "onlineIeltsPrivateLesson" },
      { "id": 550, "name": "onlineElementarySchoolMathematicsPrivateLesson" },
      { "id": 551, "name": "onlineElementarySchoolPrivateLesson" },
      { "id": 552, "name": "onlineEnglishSpeaking" },
      { "id": 553, "name": "onlineEnglishPrivateLesson" },
      { "id": 554, "name": "onlineSpanishPrivateLesson" },
      { "id": 555, "name": "onlineItalianPrivateLesson" },
      { "id": 556, "name": "onlineQuranPrivateLesson" },
      { "id": 557, "name": "onlineLgsMathematicsPrivateLesson" },
      { "id": 558, "name": "onlineHighSchoolMathematicsPrivateLesson" },
      { "id": 559, "name": "onlineAccountingLesson" },
      { "id": 560, "name": "onlineStudentCoach" },
      { "id": 561, "name": "onlineMiddleSchoolMathematicsPrivateLesson" },
      { "id": 562, "name": "onlinePersonalTrainer" },
      { "id": 563, "name": "onlinePilatesLesson" },
      { "id": 564, "name": "onlineArtLesson" },
      { "id": 565, "name": "onlineRussianPrivateLesson" },
      { "id": 566, "name": "onlineSingingLesson" },
      { "id": 567, "name": "onlineTurkishPrivateLesson" },
      { "id": 568, "name": "onlineTytMathematicsPrivateLesson" },
      { "id": 569, "name": "onlineYksCoach" },
      { "id": 570, "name": "onlineYogaLesson" },
      { "id": 571, "name": "middleSchoolMathematicsPrivateLesson" },
      { "id": 572, "name": "autismPrivateLesson" },
      { "id": 573, "name": "privateLesson" },
      { "id": 574, "name": "specialEducation" },
      { "id": 575, "name": "cakeLesson" },
      { "id": 576, "name": "skatingLesson" },
      { "id": 577, "name": "personalTrainer" },
      { "id": 578, "name": "pilatesLesson" },
      { "id": 579, "name": "pianoLesson" },
      { "id": 580, "name": "reformerPilatesLesson" },
      { "id": 581, "name": "artCourse" },
      { "id": 582, "name": "artPrivateLesson" },
      { "id": 583, "name": "russianPrivateLesson" },
      { "id": 584, "name": "singingLesson" },
      { "id": 585, "name": "chessPrivateLesson" },
      { "id": 586, "name": "classTeacher" },
      { "id": 587, "name": "sportsCoach" },
      { "id": 588, "name": "drivingCourse" },
      { "id": 589, "name": "drivingTraining" },
      { "id": 590, "name": "tennisLesson" },
      { "id": 591, "name": "turkishPrivateLesson" },
      { "id": 592, "name": "tytMathematicsPrivateLesson" },
      { "id": 593, "name": "universityPhysicsPrivateLesson" },
      { "id": 594, "name": "universityMathematicsPrivateLesson" },
      { "id": 595, "name": "fluteLesson" },
      { "id": 596, "name": "softwarePrivateLesson" },
      { "id": 597, "name": "adultSwimmingLesson" },
      { "id": 598, "name": "yogaLesson" },
      { "id": 599, "name": "swimmingLesson" },
      { "id": 600, "name": "zeybekLesson" }
    ]

  },
  {
    "id": 6,
    "name": "healthAndBeautyServices",
    "services": [
      { "id": 601, "name": "familyConsultant" },
      { "id": 602, "name": "familyConstellation" },
      { "id": 603, "name": "familyTherapy" },
      { "id": 604, "name": "addictionPsychologist" },
      { "id": 605, "name": "cognitiveBehavioralTherapy" },
      { "id": 606, "name": "bioenergySpecialist" },
      { "id": 607, "name": "coupleTherapy" },
      { "id": 608, "name": "skinCare" },
      { "id": 609, "name": "sexualTherapy" },
      { "id": 610, "name": "childCare" },
      { "id": 611, "name": "childCareAndHomeAssistant" },
      { "id": 612, "name": "childPlayGroup" },
      { "id": 613, "name": "childPsychologist" },
      { "id": 614, "name": "speechAndLanguageTherapy" },
      { "id": 615, "name": "dietitian" },
      { "id": 616, "name": "birthChartCalculation" },
      { "id": 617, "name": "tattooArtist" },
      { "id": 618, "name": "emdrTherapy" },
      { "id": 619, "name": "lactationConsultant" },
      { "id": 620, "name": "epilation" },
      { "id": 621, "name": "occupationalTherapy" },
      { "id": 622, "name": "maleEpilation" },
      { "id": 623, "name": "homeAssistant" },
      { "id": 624, "name": "homeCareServices" },
      { "id": 625, "name": "homePhysicalTherapy" },
      { "id": 626, "name": "homePatientCare" },
      { "id": 627, "name": "homeNurse" },
      { "id": 628, "name": "homeSerumInjection" },
      { "id": 629, "name": "elderlyCareAtHome" },
      { "id": 630, "name": "marriageTherapy" },
      { "id": 631, "name": "fortuneTelling" },
      { "id": 632, "name": "physiotherapist" },
      { "id": 633, "name": "brideMakeup" },
      { "id": 634, "name": "brideHair" },
      { "id": 635, "name": "patientCare" },
      { "id": 636, "name": "hospitalCompanion" },
      { "id": 637, "name": "nurse" },
      { "id": 638, "name": "hypnotherapy" },
      { "id": 639, "name": "relationshipTherapy" },
      { "id": 640, "name": "englishGameSister" },
      { "id": 641, "name": "eyelashExtensions" },
      { "id": 642, "name": "gelNail" },
      { "id": 643, "name": "permanentNailPolish" },
      { "id": 644, "name": "chiropractic" },
      { "id": 645, "name": "clinicalPsychologist" },
      { "id": 646, "name": "hairdresser" },
      { "id": 647, "name": "cuppingTherapy" },
      { "id": 648, "name": "leadCasting" },
      { "id": 649, "name": "makeupArtist" },
      { "id": 650, "name": "manualLymphaticDrainage" },
      { "id": 651, "name": "manualTherapy" },
      { "id": 652, "name": "massageForMen" },
      { "id": 653, "name": "medium" },
      { "id": 654, "name": "microWelding" },
      { "id": 655, "name": "moxoTest" },
      { "id": 656, "name": "engagementMakeup" },
      { "id": 657, "name": "onlineFamilyTherapy" },
      { "id": 658, "name": "onlineAddictionPsychologist" },
      { "id": 659, "name": "onlineCoupleTherapy" },
      { "id": 660, "name": "onlineSexualTherapy" },
      { "id": 661, "name": "onlineChildPsychologist" },
      { "id": 662, "name": "onlineSpeechAndLanguageTherapy" },
      { "id": 663, "name": "onlineDietitian" },
      { "id": 664, "name": "onlineAdolescentPsychologist" },
      { "id": 665, "name": "onlineMarriageTherapy" },
      { "id": 666, "name": "onlineCoffeeFortune" },
      { "id": 667, "name": "onlinePedagogue" },
      { "id": 668, "name": "onlinePsychologist" },
      { "id": 669, "name": "onlinePsychologicalConsultant" },
      { "id": 670, "name": "onlinePsychotherapy" },
      { "id": 671, "name": "onlineTarotFortune" },
      { "id": 672, "name": "onlineTherapy" },
      { "id": 673, "name": "onlineLifeCoach" },
      { "id": 674, "name": "gameSister" },
      { "id": 675, "name": "playTherapy" },
      { "id": 676, "name": "specialDayMakeup" },
      { "id": 677, "name": "pedagogue" },
      { "id": 678, "name": "personalTrainerLesson" },
      { "id": 679, "name": "pilatesClass" },
      { "id": 680, "name": "nailProsthesis" },
      { "id": 681, "name": "psychologist" },
      { "id": 682, "name": "psychologicalConsultant" },
      { "id": 683, "name": "psychotherapy" },
      { "id": 684, "name": "hourlyChildCare" },
      { "id": 685, "name": "hairExtensions" },
      { "id": 686, "name": "hairAndMakeup" },
      { "id": 687, "name": "thetaHealing" },
      { "id": 688, "name": "expertPsychologist" },
      { "id": 689, "name": "lifeCoach" },
      { "id": 690, "name": "elderlyCare" },
      { "id": 691, "name": "starNameReading" }
    ]

  },
  {
    "id": 7,
    "name": "organizationServices",
    "services": [
      { "id": 701, "name": "eveningDressSewing" },
      { "id": 702, "name": "openingOrganization" },
      { "id": 703, "name": "animator" },
      { "id": 704, "name": "marchingBand" },
      { "id": 705, "name": "boutiqueCake" },
      { "id": 706, "name": "liveMusic" },
      { "id": 707, "name": "catering" },
      { "id": 708, "name": "florist" },
      { "id": 709, "name": "bellyDancerRental" },
      { "id": 710, "name": "drumAndZurnaRental" },
      { "id": 711, "name": "religiousMarriageCeremony" },
      { "id": 712, "name": "dj" },
      { "id": 713, "name": "birthdayCatering" },
      { "id": 714, "name": "birthdayVenues" },
      { "id": 715, "name": "birthdayOrganization" },
      { "id": 716, "name": "birthdayCake" },
      { "id": 717, "name": "weddingOrganization" },
      { "id": 718, "name": "weddingBand" },
      { "id": 719, "name": "homeEngagementOrganization" },
      { "id": 720, "name": "homePromiseOrganization" },
      { "id": 721, "name": "weddingProposalOrganization" },
      { "id": 722, "name": "brideArrivalBand" },
      { "id": 723, "name": "brideCarRental" },
      { "id": 724, "name": "brideCarDecoration" },
      { "id": 725, "name": "weddingDress" },
      { "id": 726, "name": "weddingDressSewing" },
      { "id": 727, "name": "weddingDressRental" },
      { "id": 728, "name": "hospitalRoomDecoration" },
      { "id": 729, "name": "iftarMealCatering" },
      { "id": 730, "name": "violinistRental" },
      { "id": 731, "name": "hennaOrganization" },
      { "id": 732, "name": "goalkeeperRental" },
      { "id": 733, "name": "cocktailCatering" },
      { "id": 734, "name": "lokmaServing" },
      { "id": 735, "name": "tableChairRental" },
      { "id": 736, "name": "mevlutReading" },
      { "id": 737, "name": "mevlutPilaf" },
      { "id": 738, "name": "mevlutMeal" },
      { "id": 739, "name": "weddingFavor" },
      { "id": 740, "name": "engagementGift" },
      { "id": 741, "name": "engagementTreatsCatering" },
      { "id": 742, "name": "engagementVenues" },
      { "id": 743, "name": "engagementMenuCatering" },
      { "id": 744, "name": "engagementOrganization" },
      { "id": 745, "name": "organization" },
      { "id": 746, "name": "clown" },
      { "id": 747, "name": "cake" },
      { "id": 748, "name": "plasticTableChairRental" },
      { "id": 749, "name": "soundSystemRental" },
      { "id": 750, "name": "magician" },
      { "id": 751, "name": "setMenuMeal" },
      { "id": 752, "name": "boatRental" },
      { "id": 753, "name": "weddingOfficiant" },
      { "id": 754, "name": "yachtRental" },
      { "id": 755, "name": "yachtMarriageProposal" }
    ]

  },
  {
    "id": 8,
    "name": "photoAndVideo",
    "services": [
      { "id": 801, "name": "babyPhotographer" },
      { "id": 802, "name": "outdoorShootPhotographer" },
      { "id": 803, "name": "birthdayPhotographer" },
      { "id": 804, "name": "droneShooting" },
      { "id": 805, "name": "dronePhotographyAndVideo" },
      { "id": 806, "name": "weddingPhotographer" },
      { "id": 807, "name": "weddingVideoShooting" },
      { "id": 808, "name": "eCommercePhotography" },
      { "id": 809, "name": "photographer" },
      { "id": 810, "name": "instagramPhotography" },
      { "id": 811, "name": "cameraman" },
      { "id": 812, "name": "clipShooting" },
      { "id": 813, "name": "locationPhotographer" },
      { "id": 814, "name": "weddingPhotographerCivilCeremony" },
      { "id": 815, "name": "engagementPhotographer" },
      { "id": 816, "name": "socialMediaPhotography" },
      { "id": 817, "name": "socialMediaVideoShooting" },
      { "id": 818, "name": "promisePhotoShooting" },
      { "id": 819, "name": "promotionalVideoShooting" },
      { "id": 820, "name": "productPhotography" },
      { "id": 821, "name": "videoShooting" },
      { "id": 822, "name": "videoEditor" },
      { "id": 823, "name": "videoEditing" }
    ]

  },
  {
    "id": 9,
    "name": "digitalAndEnterprise",
    "services": [
      { "id": 901, "name": "threeDAnimationProduction" },
      { "id": 902, "name": "threeDPrinting" },
      { "id": 903, "name": "usVisaConsulting" },
      { "id": 904, "name": "posterDesign" },
      { "id": 905, "name": "germanTranslation" },
      { "id": 906, "name": "germanSwornTranslation" },
      { "id": 907, "name": "germanyVisaConsulting" },
      { "id": 908, "name": "packagingDesign" },
      { "id": 909, "name": "androidAppDevelopment" },
      { "id": 910, "name": "apartmentManagement" },
      { "id": 911, "name": "astrologyConsulting" },
      { "id": 912, "name": "autocadDrawing" },
      { "id": 913, "name": "brochurePrinting" },
      { "id": 914, "name": "brochureDistribution" },
      { "id": 915, "name": "brochureDesign" },
      { "id": 916, "name": "glassCladding" },
      { "id": 917, "name": "cvPreparationConsulting" },
      { "id": 918, "name": "invitationPrinting" },
      { "id": 919, "name": "digitalPrinting" },
      { "id": 920, "name": "digitalMarketing" },
      { "id": 921, "name": "wallPainting" },
      { "id": 922, "name": "eCommerceConsultant" },
      { "id": 923, "name": "dressMaking" },
      { "id": 924, "name": "electronicCircuitDesign" },
      { "id": 925, "name": "realEstateSalesConsultant" },
      { "id": 926, "name": "etsyConsultant" },
      { "id": 927, "name": "contractCosmeticProduction" },
      { "id": 928, "name": "franceVisaConsulting" },
      { "id": 929, "name": "freelanceDeveloper" },
      { "id": 930, "name": "fairHostess" },
      { "id": 931, "name": "googleAdManagement" },
      { "id": 932, "name": "graffiti" },
      { "id": 933, "name": "graphicDesign" },
      { "id": 934, "name": "customsConsultant" },
      { "id": 935, "name": "interiorDesignConsulting" },
      { "id": 936, "name": "illustrationDrawing" },
      { "id": 937, "name": "englishTranslation" },
      { "id": 938, "name": "englishSwornTranslation" },
      { "id": 939, "name": "ukVisaConsulting" },
      { "id": 940, "name": "instagramAccountRecovery" },
      { "id": 941, "name": "occupationalHealthAndSafety" },
      { "id": 942, "name": "illuminatedSignage" },
      { "id": 943, "name": "femaleModel" },
      { "id": 944, "name": "pencilDrawing" },
      { "id": 945, "name": "businessCardPrinting" },
      { "id": 946, "name": "businessCardDesign" },
      { "id": 947, "name": "catalogDesign" },
      { "id": 948, "name": "bookPrinting" },
      { "id": 949, "name": "kosgebConsulting" },
      { "id": 950, "name": "corporateLogoDesign" },
      { "id": 951, "name": "boxLetterSignage" },
      { "id": 952, "name": "limitedCompanyEstablishment" },
      { "id": 953, "name": "logoDesign" },
      { "id": 954, "name": "brandRegistration" },
      { "id": 955, "name": "copywriting" },
      { "id": 956, "name": "existingWebsiteEditing" },
      { "id": 957, "name": "mobileAppDevelopment" },
      { "id": 958, "name": "fashionDesign" },
      { "id": 959, "name": "musicProduction" },
      { "id": 960, "name": "preAccounting" },
      { "id": 961, "name": "ottomanTranslation" },
      { "id": 962, "name": "gameProgramming" },
      { "id": 963, "name": "privateProtection" },
      { "id": 964, "name": "privateHealthInsurance" },
      { "id": 965, "name": "photoshopSpecialist" },
      { "id": 966, "name": "advertisingAgency" },
      { "id": 967, "name": "painter" },
      { "id": 968, "name": "russianTranslation" },
      { "id": 969, "name": "personalCompanyEstablishment" },
      { "id": 970, "name": "seoService" },
      { "id": 971, "name": "seoFriendlyArticleWriting" },
      { "id": 972, "name": "voiceOver" },
      { "id": 973, "name": "socialSecurityConsulting" },
      { "id": 974, "name": "insuranceAgency" },
      { "id": 975, "name": "companyEstablishment" },
      { "id": 976, "name": "socialMediaConsulting" },
      { "id": 977, "name": "socialMediaDesign" },
      { "id": 978, "name": "socialMediaSpecialist" },
      { "id": 979, "name": "socialMediaManagementAndConsulting" },
      { "id": 980, "name": "spssAnalysis" },
      { "id": 981, "name": "studioRecording" },
      { "id": 982, "name": "presentationPreparation" },
      { "id": 983, "name": "sweatshirtProduction" },
      { "id": 984, "name": "signage" },
      { "id": 985, "name": "translation" },
      { "id": 986, "name": "tailor" },
      { "id": 987, "name": "tShirtPrinting" },
      { "id": 988, "name": "tShirtProduction" },
      { "id": 989, "name": "tShirtDesign" },
      { "id": 990, "name": "trafficInsurance" },
      { "id": 991, "name": "visaApplication" },
      { "id": 992, "name": "websiteDevelopment" },
      { "id": 993, "name": "webDesign" },
      { "id": 994, "name": "webDesignProgramming" },
      { "id": 995, "name": "webSoftware" },
      { "id": 996, "name": "websiteDesign" },
      { "id": 997, "name": "softwareDevelopment" },
      { "id": 998, "name": "universityChoiceConsultant" },
      { "id": 999, "name": "greeceVisaConsulting" }
    ]
  },
  {
  "id": 10,
  "name": "pets",
    "services": [
      { "id": 701, "name": "homeCatCare" },
      { "id": 702, "name": "catCare" },
      { "id": 703, "name": "catHotel" },
      { "id": 704, "name": "catGrooming" },
      { "id": 705, "name": "dogTraining" },
      { "id": 706, "name": "dogWalking" },
      { "id": 707, "name": "dogGrooming" },
      { "id": 708, "name": "dogHotel" },
      { "id": 709, "name": "dogBoarding" },
      { "id": 710, "name": "dogCutGrooming" },
      { "id": 711, "name": "petGrooming" }
    ]

  },
  {
    "id": 11,
    "name": "autoAndVehicle",
    "services": [
      { "id": 701, "name": "vehicleMaintenance" },
      { "id": 702, "name": "vehicleWrap" },
      { "id": 703, "name": "vehicleCoating" },
      { "id": 704, "name": "vehicleSeatCleaning" },
      { "id": 705, "name": "vehiclePpfCoating" },
      { "id": 706, "name": "vehicleCeramicCoating" },
      { "id": 707, "name": "brakePadChange" },
      { "id": 708, "name": "pressBrakePadChange" },
      { "id": 709, "name": "paintlessDentRepair" },
      { "id": 710, "name": "windowTint" },
      { "id": 711, "name": "detailedVehicleCleaning" },
      { "id": 712, "name": "tireRepair" },
      { "id": 713, "name": "engineGasketChange" },
      { "id": 714, "name": "engineRepair" },
      { "id": 715, "name": "engineOilChange" },
      { "id": 716, "name": "carPaint" },
      { "id": 717, "name": "carWindowTint" },
      { "id": 718, "name": "carInspection" },
      { "id": 719, "name": "carElectrical" },
      { "id": 720, "name": "carBodyPaint" },
      { "id": 721, "name": "carAirConditionerRepair" },
      { "id": 722, "name": "carDetailing" },
      { "id": 723, "name": "carTire" },
      { "id": 724, "name": "carRepair" },
      { "id": 725, "name": "polishAndWax" },
      { "id": 726, "name": "ceramicCoating" },
      { "id": 727, "name": "timingBeltSetChange" }
    ]

  },
  {
    "id": 12,
    "name": "other",
    "services": [
      { "id": 601, "name": "threeDimensionalArchitecturalModeling" },
      { "id": 602, "name": "threeDimensionalRendering" },
      { "id": 603, "name": "threeDimensionalProductModeling" },
      { "id": 604, "name": "builtInStoveMarbleCutting" },
      { "id": 605, "name": "reinforcedConcreteHouseConstruction" },
      { "id": 606, "name": "washingMachineWaterLeak" },
      { "id": 607, "name": "birthChartInterpretation" },
      { "id": 608, "name": "showerCabinInstallationIncluded" },
      { "id": 609, "name": "wallPaintingg" },
      { "id": 610, "name": "realEstateDroneShooting" },
      { "id": 611, "name": "realEstateAgent" },
      { "id": 612, "name": "etsyStoreOpening" },
      { "id": 613, "name": "homemade" },
      { "id": 614, "name": "musicalGroup" },
      { "id": 615, "name": "financialAdvisor" },
      { "id": 616, "name": "realEstateConsultant" },
      { "id": 617, "name": "realEstateValuation" },
      { "id": 618, "name": "googleAdsSpecialist" },
      { "id": 619, "name": "solarWaterHeating" },
      { "id": 620, "name": "solarPanel" },
      { "id": 621, "name": "imamMarriageOfficiation" },
      { "id": 622, "name": "instagramAdManagement" },
      { "id": 623, "name": "websiteCreation" },
      { "id": 624, "name": "cameraInstallation" },
      { "id": 625, "name": "caravanRental" },
      { "id": 626, "name": "lgsPreparation" },
      { "id": 627, "name": "metaphysicalExpert" },
      { "id": 628, "name": "onlineFamilyCounselor" },
      { "id": 629, "name": "onlinePreAccounting" },
      { "id": 630, "name": "lawnMowing" },
      { "id": 631, "name": "privateDetective" },
      { "id": 632, "name": "cakeService" },
      { "id": 633, "name": "playstationRental" },
      { "id": 634, "name": "projectWriting" },
      { "id": 635, "name": "chairUpholstery" },
      { "id": 636, "name": "siteManagement" },
      { "id": 637, "name": "socialMediaAgency" },
      { "id": 638, "name": "contractPreparation" },
      { "id": 639, "name": "pastryChef" },
      { "id": 640, "name": "awning" },
      { "id": 641, "name": "soilFilling" },
      { "id": 642, "name": "trioMusicGroup" },
      { "id": 643, "name": "vitoWeddingCarRental" },
      { "id": 644, "name": "foreignWorkPermit" },
      { "id": 645, "name": "oilPaintingArtCreation" },
      { "id": 646, "name": "bedroomSetPainting" },
      { "id": 647, "name": "softwareDeveloper" },
      { "id": 648, "name": "yksCoach" },
      { "id": 649, "name": "storageCabinetCreation" }
    ]
  }
]

